llm_auto_eda/__init__.py
llm_auto_eda/main.py
llm_auto_eda/core/__init__.py
llm_auto_eda/core/analyzer.py
llm_auto_eda/core/data_loader.py
llm_auto_eda/core/llm_analyzer.py
llm_auto_eda/core/report_generator.py
llm_auto_eda/core/statistical_analyzer.py
llm_auto_eda/core/visualizer.py
llm_auto_eda-0.0.3.dist-info/LICENSE
llm_auto_eda-0.0.3.dist-info/METADATA
llm_auto_eda-0.0.3.dist-info/WHEEL
llm_auto_eda-0.0.3.dist-info/top_level.txt
llm_auto_eda-0.0.3.dist-info/RECORD
