Metadata-Version: 2.2
Name: llm-auto-eda
Version: 0.0.3
Summary: An intelligent automated exploratory data analysis tool powered by Large Language Models, providing in-depth insights and visualizations for your datasets
Home-page: https://github.com/enesmanan/LLMAutoEDA
Author: Enes Fehmi Manan
Author-email: enesmanan768@gmail.com
Classifier: Programming Language :: Python :: 3
Classifier: License :: OSI Approved :: MIT License
Classifier: Operating System :: OS Independent
Requires-Python: >=3.7
License-File: LICENSE
Requires-Dist: pandas
Requires-Dist: numpy
Requires-Dist: plotly
Requires-Dist: jinja2
Requires-Dist: openai
Requires-Dist: ipython
Requires-Dist: markdown2
Requires-Dist: scipy
Requires-Dist: pathlib
Dynamic: author
Dynamic: author-email
Dynamic: classifier
Dynamic: description
Dynamic: description-content-type
Dynamic: home-page
Dynamic: requires-dist
Dynamic: requires-python
Dynamic: summary
